sailfish/__init__.py
sailfish/sailfish.py
sailfish/_common/BaseStage.py
sailfish/_common/OpsFactory.py
sailfish/_common/__init__.py
sailfish/_common/_factory.py
sailfish/_common/decorators.py
sailfish/io/__init__.py
sailfish/ops/__init__.py
sailfish/utils/__init__.py
sailfish/utils/configure_logger.py
sailfish/utils/memory_usage.py
sailfish/utils/normalize_column_names.py
sailfish/utils/np_float_scalars.py
sailfish/utils/np_int_scalars.py
sailfish-0.0.1.dist-info/METADATA
sailfish-0.0.1.dist-info/WHEEL
sailfish-0.0.1.dist-info/top_level.txt
sailfish-0.0.1.dist-info/RECORD
