Metadata-Version: 2.1
Name: sailfish
Version: 0.0.1
Summary: Sailfish provides helpful utilities and pipelines to optimize Pandas dataframes. This Sailfish projectreplaces pd-helper 1.0.0 which is deprecated with sailfish 1.0.0.
Home-page: https://github.com/justinhchae/sailfish
Author: Justin Chae
Author-email: justin.chae@dyna-lab.com
License: UNKNOWN
Project-URL: Download URL, https://github.com/justinhchae/sailfish/archive/refs/tags/0.0.2.tar.gz
Platform: UNKNOWN
Classifier: Development Status :: 4 - Beta
Classifier: Programming Language :: Python :: 3
Classifier: License :: OSI Approved :: MIT License
Classifier: Operating System :: OS Independent
Classifier: Intended Audience :: Developers
Classifier: Topic :: Scientific/Engineering :: Information Analysis
Requires-Python: >=3.7
Requires-Dist: pandas
Requires-Dist: numpy
Requires-Dist: tqdm
Requires-Dist: shortuuid
